Workbook

Sheet system_config
A1: key | B1: value | C1: comment
A2: CEO_FINANCE_CORE_SHEET_ID | B2: 10SYmxcbbaevfnG8I5e3L1vh-L5F2qbazi37kLpu4FOc | C2: ID этого файла Google Sheets после загрузки.
A3: OPS_DB_SHEET_ID | B3: 1fQovsTmvYufuNeGKClq22Z8z-xHTvQ-OdJLDlm5eUDM | C3: ID OPS_DB (операционная база фактов).
A4: CONTROL_MODEL_SHEET_ID | B4: 1IpRlrfFCKUF1mM0RG24nk2IibcoxyzV6rZc7ZB227RU | C4: ID Control Model (правила/пороги/роли).
A5: TIMEZONE | B5: Europe/Berlin | C5: Таймзона для дат/периодов.
A6: ENV | B6: prod | C6: Окружение: dev/prod.
A7: CASHFLOW_CLOSE_FREQUENCY | B7: weekly | C7: Частота закрытия ДДС: daily/weekly/monthly.
A8: PNL_CLOSE_FREQUENCY | B8: monthly | C8: Частота закрытия P&L: weekly/monthly.
A9: NOTE | B9: Не дублируй users_roles/RBAC здесь. Только финансы + ссылки по user_id/sku_id. | C9: Памятка для разработки.

Sheet data_sources
A1: entity | B1: source_table | C1: source_sheet_id_key | D1: refresh_mode | E1: used_in_sheets | F1: comment
A2: shipments_aggregates | B2: OPS_DB.shipments | C2: OPS_DB_SHEET_ID | D2: read-only | E2: P&L_CEO;Scaling_Control | F2: Риски/готовность для связи операций и финансов.
A3: inventory_value | B3: OPS_DB.inventory_balances | C3: OPS_DB_SHEET_ID | D3: optional | E3: P&L_CEO | F3: Если считаем баланс/запасы.
A4: payroll_facts | B4: OPS_DB.salary_facts (если будет) | C4: OPS_DB_SHEET_ID | D4: future(P1) | E4: P&L_CEO | F4: Подтягивание начислений.

Sheet Cash_Flow
A1: Дата | B1: Остаток на начало | C1: Всего поступлений | D1: Всего списаний | E1: Чистый поток | F1: Остаток на конец | G1: Ozon | H1: WB | I1: Яндекс Маркет | J1: Офлайн | K1: Прочие | L1: Закупки | M1: Зарплата | N1: Логистика | O1: Маркетинг | P1: Аренда | Q1: Налоги | R1: Прочее | T1: CEO Финансовые индикаторы
A2: 2026-02-01 | B2: 650000 | C2: =SUM(G2:K2) -> 285000 | D2: =SUM(L2:R2) -> 75000 | E2: =C2-D2 -> 210000 | F2: =B2+E2 -> 860000 | G2: 110000 | H2: 85000 | I2: 55000 | J2: 35000 | K2: 0 | L2: 75000 | M2: 0 | N2: 0 | O2: 0 | P2: 0 | Q2: 0 | R2: 0 | T2: MIN_CASH | U2: 350000
A3: 2026-02-02 | B3: =F2 -> 860000 | C3: =SUM(G3:K3) -> 0 | D3: =SUM(L3:R3) -> 0 | E3: =C3-D3 -> 0 | F3: =B3+E3 -> 860000 | G3: 0 | H3: 0 | I3: 0 | J3: 0 | K3: 0 | L3: 0 | M3: 0 | N3: 0 | O3: 0 | P3: 0 | Q3: 0 | R3: 0 | T3: Дата_сегодня | U3: 2026-02-01
A4: 2026-02-03 | B4: =F3 -> 860000 | C4: =SUM(G4:K4) -> 0 | D4: =SUM(L4:R4) -> 22000 | E4: =C4-D4 -> -22000 | F4: =B4+E4 -> 838000 | G4: 0 | H4: 0 | I4: 0 | J4: 0 | K4: 0 | L4: 0 | M4: 0 | N4: 22000 | O4: 0 | P4: 0 | Q4: 0 | R4: 0 | T4: Остаток сегодня | U4: {=XLOOKUP(U3,A:A,F:F,,0)} -> 860000
A5: 2026-02-04 | B5: =F4 -> 838000 | C5: =SUM(G5:K5) -> 110000 | D5: =SUM(L5:R5) -> 45000 | E5: =C5-D5 -> 65000 | F5: =B5+E5 -> 903000 | G5: 110000 | H5: 0 | I5: 0 | J5: 0 | K5: 0 | L5: 0 | M5: 0 | N5: 0 | O5: 45000 | P5: 0 | Q5: 0 | R5: 0 | T5: CASH_14 | U5: {=XLOOKUP(U3+14,A:A,F:F,,0)}
A6: 2026-02-05 | B6: =F5 -> 903000 | C6: =SUM(G6:K6) -> 85000 | D6: =SUM(L6:R6) -> 30000 | E6: =C6-D6 -> 55000 | F6: =B6+E6 -> 958000 | G6: 0 | H6: 85000 | I6: 0 | J6: 0 | K6: 0 | L6: 0 | M6: 0 | N6: 0 | O6: 0 | P6: 30000 | Q6: 0 | R6: 0 | T6: FREE_CASH | U6: =U4-SUMIFS(Payment_Calendar!D:D,Payment_Calendar!H:H,1,Payment_Calendar!A:A,">="&U3,Payment_Calendar!A:A,"<="&U3+14,Payment_Calendar!F:F,"<>Оплачен") -> 860000
A7: 2026-02-06 | B7: =F6 -> 958000 | C7: =SUM(G7:K7) -> 55000 | D7: =SUM(L7:R7) -> 0 | E7: =C7-D7 -> 55000 | F7: =B7+E7 -> 1013000 | G7: 0 | H7: 0 | I7: 55000 | J7: 0 | K7: 0 | L7: 0 | M7: 0 | N7: 0 | O7: 0 | P7: 0 | Q7: 0 | R7: 0
A8: 2026-02-07 | B8: =F7 -> 1013000 | C8: =SUM(G8:K8) -> 145000 | D8: =SUM(L8:R8) -> 75000 | E8: =C8-D8 -> 70000 | F8: =B8+E8 -> 1083000 | G8: 110000 | H8: 0 | I8: 0 | J8: 35000 | K8: 0 | L8: 75000 | M8: 0 | N8: 0 | O8: 0 | P8: 0 | Q8: 0 | R8: 0
A9: 2026-02-08 | B9: =F8 -> 1083000 | C9: =SUM(G9:K9) -> 0 | D9: =SUM(L9:R9) -> 22000 | E9: =C9-D9 -> -22000 | F9: =B9+E9 -> 1061000 | G9: 0 | H9: 0 | I9: 0 | J9: 0 | K9: 0 | L9: 0 | M9: 0 | N9: 22000 | O9: 0 | P9: 0 | Q9: 0 | R9: 0
A10: 2026-02-09 | B10: =F9 -> 1061000 | C10: =SUM(G10:K10) -> 85000 | D10: =SUM(L10:R10) -> 0 | E10: =C10-D10 -> 85000 | F10: =B10+E10 -> 1146000 | G10: 0 | H10: 85000 | I10: 0 | J10: 0 | K10: 0 | L10: 0 | M10: 0 | N10: 0 | O10: 0 | P10: 0 | Q10: 0 | R10: 0
A11: 2026-02-10 | B11: =F10 -> 1146000 | C11: =SUM(G11:K11) -> 110000 | D11: =SUM(L11:R11) -> 160000 | E11: =C11-D11 -> -50000 | F11: =B11+E11 -> 1096000 | G11: 110000 | H11: 0 | I11: 0 | J11: 0 | K11: 0 | L11: 0 | M11: 160000 | N11: 0 | O11: 0 | P11: 0 | Q11: 0 | R11: 0
A12: 2026-02-11 | B12: =F11 -> 1096000 | C12: =SUM(G12:K12) -> 55000 | D12: =SUM(L12:R12) -> 45000 | E12: =C12-D12 -> 10000 | F12: =B12+E12 -> 1106000 | G12: 0 | H12: 0 | I12: 55000 | J12: 0 | K12: 0 | L12: 0 | M12: 0 | N12: 0 | O12: 45000 | P12: 0 | Q12: 0 | R12: 0
A13: 2026-02-12 | B13: =F12 -> 1106000 | C13: =SUM(G13:K13) -> 0 | D13: =SUM(L13:R13) -> 0 | E13: =C13-D13 -> 0 | F13: =B13+E13 -> 1106000 | G13: 0 | H13: 0 | I13: 0 | J13: 0 | K13: 0 | L13: 0 | M13: 0 | N13: 0 | O13: 0 | P13: 0 | Q13: 0 | R13: 0
A14: 2026-02-13 | B14: =F13 -> 1106000 | C14: =SUM(G14:K14) -> 230000 | D14: =SUM(L14:R14) -> 97000 | E14: =C14-D14 -> 133000 | F14: =B14+E14 -> 1239000 | G14: 110000 | H14: 85000 | I14: 0 | J14: 35000 | K14: 0 | L14: 75000 | M14: 0 | N14: 22000 | O14: 0 | P14: 0 | Q14: 0 | R14: 0
A15: 2026-02-14 | B15: =F14 -> 1239000 | C15: =SUM(G15:K15) -> 0 | D15: =SUM(L15:R15) -> 0 | E15: =C15-D15 -> 0 | F15: =B15+E15 -> 1239000 | G15: 0 | H15: 0 | I15: 0 | J15: 0 | K15: 0 | L15: 0 | M15: 0 | N15: 0 | O15: 0 | P15: 0 | Q15: 0 | R15: 0
A16: 2026-02-15 | B16: =F15 -> 1239000 | C16: =SUM(G16:K16) -> 0 | D16: =SUM(L16:R16) -> 95000 | E16: =C16-D16 -> -95000 | F16: =B16+E16 -> 1144000 | G16: 0 | H16: 0 | I16: 0 | J16: 0 | K16: 0 | L16: 0 | M16: 0 | N16: 0 | O16: 0 | P16: 0 | Q16: 95000 | R16: 0
A17: 2026-02-16 | B17: =F16 -> 1144000 | C17: =SUM(G17:K17) -> 165000 | D17: =SUM(L17:R17) -> 0 | E17: =C17-D17 -> 165000 | F17: =B17+E17 -> 1309000 | G17: 110000 | H17: 0 | I17: 55000 | J17: 0 | K17: 0 | L17: 0 | M17: 0 | N17: 0 | O17: 0 | P17: 0 | Q17: 0 | R17: 0
A18: 2026-02-17 | B18: =F17 -> 1309000 | C18: =SUM(G18:K18) -> 85000 | D18: =SUM(L18:R18) -> 0 | E18: =C18-D18 -> 85000 | F18: =B18+E18 -> 1394000 | G18: 0 | H18: 85000 | I18: 0 | J18: 0 | K18: 0 | L18: 0 | M18: 0 | N18: 0 | O18: 0 | P18: 0 | Q18: 0 | R18: 0
... A31: 2026-03-02 | B31: =F30 -> 1803000 | C31: =SUM(G31:K31) -> 0 | D31: =SUM(L31:R31) -> 0 | E31: =C31-D31 -> 0 | F31: =B31+E31 -> 1803000 | G31: 0 | H31: 0 | I31: 0 | J31: 0 | K31: 0 | L31: 0 | M31: 0 | N31: 0 | O31: 0 | P31: 0 | Q31: 0 | R31: 0

Sheet Payment_Calendar
A1: Дата | B1: Контрагент | C1: Назначение | D1: Сумма | E1: Тип | F1: Статус | G1: Можно сдвинуть | H1: Приоритет | I1: Комментарий
A2: 2026-02-01 | B2: Поставщик | C2: Сырьё | D2: 75000 | E2: Закупки | F2: Запланирован | G2: Да | H2: 2 | I2: Можно сдвигать
A3: 2026-02-03 | B3: Логистика | C3: Доставка | D3: 22000 | E3: Логистика | F3: Запланирован | G3: Да | H3: 3
A4: 2026-02-04 | B4: Реклама | C4: Маркетинг | D4: 45000 | E4: Маркетинг | F4: Запланирован | G4: Да | H4: 3 | I4: Не срочно
A5: 2026-02-05 | B5: Арендодатель | C5: Аренда | D5: 30000 | E5: Аренда | F5: Запланирован | G5: Нет | H5: 1 | I5: Обязательно
A6: 2026-02-07 | B6: Поставщик | C6: Сырьё | D6: 75000 | E6: Закупки | F6: Запланирован | G6: Да | H6: 2 | I6: Можно сдвигать
A7: 2026-02-08 | B7: Логистика | C7: Доставка | D7: 22000 | E7: Логистика | F7: Запланирован | G7: Да | H7: 3
A8: 2026-02-10 | B8: Команда | C8: Зарплата | D8: 160000 | E8: Зарплата | F8: Запланирован | G8: Нет | H8: 1 | I8: ФОТ
A9: 2026-02-11 | B9: Реклама | C9: Маркетинг | D9: 45000 | E9: Маркетинг | F9: Запланирован | G9: Да | H9: 3 | I9: Не срочно
A10: 2026-02-13 | B10: Поставщик | C10: Сырьё | D10: 75000 | E10: Закупки | F10: Запланирован | G10: Да | H10: 2 | I10: Можно сдвигать
A11: 2026-02-13 | B11: Логистика | C11: Доставка | D11: 22000 | E11: Логистика | F11: Запланирован | G11: Да | H11: 3
A12: 2026-02-15 | B12: ФНС | C12: Налоги | D12: 95000 | E12: Налоги | F12: Запланирован | G12: Нет | H12: 1 | I12: УСН
A13: 2026-02-18 | B13: Реклама | C13: Маркетинг | D13: 45000 | E13: Маркетинг | F13: Запланирован | G13: Да | H13: 3 | I13: Не срочно
A14: 2026-02-18 | B14: Логистика | C14: Доставка | D14: 22000 | E14: Логистика | F14: Запланирован | G14: Да | H14: 3
A15: 2026-02-19 | B15: Поставщик | C15: Сырьё | D15: 75000 | E15: Закупки | F15: Запланирован | G15: Да | H15: 2 | I15: Можно сдвигать
A16: 2026-02-23 | B16: Логистика | C16: Доставка | D16: 22000 | E16: Логистика | F16: Запланирован | G16: Да | H16: 3
A17: 2026-02-25 | B17: Команда | C17: Зарплата | D17: 160000 | E17: Зарплата | F17: Запланирован | G17: Нет | H17: 1 | I17: ФОТ
A18: 2026-02-25 | B18: Поставщик | C18: Сырьё | D18: 75000 | E18: Закупки | F18: Запланирован | G18: Да | H18: 2 | I18: Можно сдвигать
A19: 2026-02-25 | B19: Реклама | C19: Маркетинг | D19: 45000 | E19: Маркетинг | F19: Запланирован | G19: Да | H19: 3 | I19: Не срочно
A20: 2026-02-28 | B20: Логистика | C20: Доставка | D20: 22000 | E20: Логистика | F20: Запланирован | G20: Да | H20: 3

Sheet P&L_CEO
A1: Месяц | B1: Канал | C1: Бренд | D1: SKU-группа | E1: Выручка | F1: Себестоимость | G1: Переменные | H1: Маржинальная прибыль | I1: Маржа %
A2: 2026-01 | B2: Ozon | C2: Solace | D2: Основной | E2: 1500000 | F2: 480000 | G2: 420000 | H2: =E2-F2-G2 -> 600000 | I2: =H2/E2 -> 0.4
A3: 2026-01 | B3: WB | C3: Solace | D3: Основной | E3: 1050000 | F3: 350000 | G3: 310000 | H3: =E3-F3-G3 -> 390000 | I3: =H3/E3 -> 0.37142857
A4: 2026-01 | B4: Яндекс Маркет | C4: Solace | D4: Основной | E4: 520000 | F4: 190000 | G4: 170000 | H4: =E4-F4-G4 -> 160000 | I4: =H4/E4 -> 0.30769231
A5: 2026-01 | B5: Офлайн | C5: Solace | D5: Наборы | E5: 260000 | F5: 110000 | G5: 30000 | H5: =E5-F5-G5 -> 120000 | I5: =H5/E5 -> 0.46153846
A6: 2026-01 | B6: Все | C6: Lolsoap | D6: Распродажа | E6: 180000 | F6: 140000 | G6: 25000 | H6: =E6-F6-G6 -> 15000 | I6: =H6/E6 -> 0.083333333

Sheet Scaling_Control
A1: АВТО-РЕЖИМ МАСШТАБИРОВАНИЯ CEO
A2: Показатель | B2: Условие | C2: Факт
A3: CASH_14 ≥ 1.5×MIN_CASH | B3: =Cash_Flow!U5>=1.5*Cash_Flow!U2 -> FALSE | C3: ==Cash_Flow!U5>=1.5*Cash_Flow!U2 -> #ERROR!
A4: FREE_CASH ≥ 1× постоянные расходы | B4: =Cash_Flow!U6>=Cash_Flow!U2/2 -> TRUE | C4: ==Cash_Flow!U6>=Cash_Flow!U2/2 -> #ERROR!
A5: Маржа ≥ 20% | B5: =AVERAGE(P&L_CEO!I2:I6)>=0.2 -> #NAME? | C5: ==AVERAGE(P&L_CEO!I2:I6)>=0.2 -> #ERROR!
A6: CASH_14 ≥ 3×MIN_CASH (x3) | B6: =Cash_Flow!U5>=3*Cash_Flow!U2 -> FALSE | C6: ==Cash_Flow!U5>=3*Cash_Flow!U2 -> #ERROR!
A7: FREE_CASH ≥ 2× пост.расходы (x3) | B7: =Cash_Flow!U6>=Cash_Flow!U2 -> TRUE | C7: ==Cash_Flow!U6>=Cash_Flow!U2 -> #ERROR!
A9: РЕЖИМ | B9: =IF(AND(C6,C7),"ЗЕЛЁНЫЙ x3",IF(AND(C3,C4,C5),"ЗЕЛЁНЫЙ x2",IF(OR(Cash_Flow!U5<Cash_Flow!U2,Cash_Flow!U6<=0),"КРАСНЫЙ","ЖЁЛТЫЙ"))) -> #ERROR!
A10: РЕШЕНИЕ | B10: =IF(B9="ЗЕЛЁНЫЙ x3","Разрешён рост x3: новые каналы, найм, рынки",IF(B9="ЗЕЛЁНЫЙ x2","Разрешён рост x2: масштабировать работающую модель",IF(B9="ЖЁЛТЫЙ","Только стабилизация и подготовка","Рост запрещён. Экономия и контроль"))) -> #ERROR!

Sheet Scaling_Scenarios
A1: Режим | B1: Что МОЖНО | C1: Что НЕЛЬЗЯ | D1: Фокус CEO
A2: КРАСНЫЙ | B2: Сокращение затрат, сдвиг платежей, чистка SKU | C2: Рост, найм, новые каналы | D2: Выживание и ликвидность
A3: ЖЁЛТЫЙ | B3: Оптимизация, тесты без роста расходов | C3: Масштабирование, расширение | D3: Подготовка системы
A4: ЗЕЛЁНЫЙ x2 | B4: Рост объёма, усиление ТОП-SKU | C4: Новые рынки, агрессивный найм | D4: Удвоение модели
A5: ЗЕЛЁНЫЙ x3 | B5: Новые рынки, каналы, команда | C5: Хаотичный рост | D5: Построение компании

Sheet CEO_Reglament
A1: Период | B1: Правило
A2: Ежедневно | B2: Проверить режим масштабирования. Если не зелёный — рост запрещён.
A3: Перед решением | B3: Любое расширение возможно ТОЛЬКО при зелёном режиме.
A4: Зелёный x2 | B4: Разрешён рост только по одному вектору.
A5: Зелёный x3 | B5: Разрешены новые рынки, найм и инвестиции.
A6: Красный | B6: Фокус только на деньгах и обязательствах.
